sscanblue/__init__.py
sscanblue/core.py
sscanblue/devices.py
sscanblue/plans.py
sscanblue/sscan1blue.py
sscanblue/utils.py
sscanblue/tests/__init__.py
sscanblue/tests/_common.py
sscanblue/tests/test_core.py
sscanblue/tests/test_devices.py
sscanblue/tests/test_plans.py
sscanblue/tests/test_utils.py
sscanblue-0.1.1.dist-info/METADATA
sscanblue-0.1.1.dist-info/WHEEL
sscanblue-0.1.1.dist-info/entry_points.txt
sscanblue-0.1.1.dist-info/top_level.txt
sscanblue-0.1.1.dist-info/RECORD
