Metadata-Version: 2.4
Name: sscanblue
Version: 0.1.1
Summary: Execute pre-configured EPICS/synApps sscans using Bluesky.
Author: BCDA
Maintainer: Pete Jemian
License-Expression: LicenseRef-ANL-Open-Source-License
Project-URL: Homepage, https://github.com/BCDA-APS/sscanblue/
Project-URL: Bug Tracker, https://github.com/BCDA-APS/sscanblue/issues
Keywords: EPICS,synApps,sscan,data acquisition,bluesky
Classifier: Development Status :: 6 - Mature
Classifier: Environment :: Console
Classifier: Intended Audience :: Science/Research
Classifier: Programming Language :: Python :: 3
Classifier: Topic :: Scientific/Engineering
Classifier: Topic :: Software Development :: Embedded Systems
Classifier: Topic :: Software Development :: Libraries :: Python Modules
Classifier: Topic :: Utilities
Requires-Python: >=3.11
Requires-Dist: apstools
Requires-Dist: bluesky
Requires-Dist: databroker
Requires-Dist: ophyd
Requires-Dist: pyRestTable
Requires-Dist: pyzmq
Provides-Extra: dev
Requires-Dist: build; extra == "dev"
Requires-Dist: coverage; extra == "dev"
Requires-Dist: coveralls; extra == "dev"
Requires-Dist: isort; extra == "dev"
Requires-Dist: mypy; extra == "dev"
Requires-Dist: pre-commit; extra == "dev"
Requires-Dist: pytest; extra == "dev"
Requires-Dist: ruff; extra == "dev"
Provides-Extra: doc
Requires-Dist: ipython; extra == "doc"
Requires-Dist: jinja2>=3.0; extra == "doc"
Requires-Dist: markupsafe==2.0.1; extra == "doc"
Requires-Dist: myst-parser; extra == "doc"
Requires-Dist: nbsphinx; extra == "doc"
Requires-Dist: pydata-sphinx-theme; extra == "doc"
Requires-Dist: pygments>=2.12; extra == "doc"
Requires-Dist: pygments-ipython-console; extra == "doc"
Requires-Dist: setuptools-scm; extra == "doc"
Requires-Dist: sphinx; extra == "doc"
Requires-Dist: sphinx-design; extra == "doc"
Provides-Extra: all
Requires-Dist: sscanblue[dev,doc]; extra == "all"
